fenbux/__init__.py
fenbux/config.py
fenbux/random_utils.py
fenbux/tree_utils.py
fenbux/typing.py
fenbux/bijector/__init__.py
fenbux/bijector/_abstract_impls.py
fenbux/bijector/_base.py
fenbux/bijector/_chain.py
fenbux/bijector/_exp_log.py
fenbux/bijector/_identity.py
fenbux/bijector/_inverse.py
fenbux/bijector/_leaky_relu.py
fenbux/bijector/_logit.py
fenbux/bijector/_reshape.py
fenbux/bijector/_scale.py
fenbux/bijector/_shift.py
fenbux/bijector/_tanh.py
fenbux/bijector/_typing.py
fenbux/core/__init__.py
fenbux/core/_abstract_impls.py
fenbux/core/_dist.py
fenbux/core/_evaluation.py
fenbux/core/_statistics.py
fenbux/core/_transformation.py
fenbux/core/_typing.py
fenbux/dist_math/__init__.py
fenbux/dist_math/bernoulli.py
fenbux/dist_math/beta.py
fenbux/dist_math/betabinom.py
fenbux/dist_math/binomial.py
fenbux/dist_math/cauchy.py
fenbux/dist_math/chi2.py
fenbux/dist_math/dirichlet.py
fenbux/dist_math/exp.py
fenbux/dist_math/f.py
fenbux/dist_math/gamma.py
fenbux/dist_math/geometry.py
fenbux/dist_math/laplace.py
fenbux/dist_math/logistic.py
fenbux/dist_math/lognormal.py
fenbux/dist_math/mvnormal.py
fenbux/dist_math/normal.py
fenbux/dist_math/pareto.py
fenbux/dist_math/poisson.py
fenbux/dist_math/t.py
fenbux/dist_math/uniform.py
fenbux/dist_math/wald.py
fenbux/dist_math/weibull.py
fenbux/extension/__init__.py
fenbux/extension/_jax_random_ext.py
fenbux/extension/_jax_special_ext.py
fenbux/multivariate/__init__.py
fenbux/multivariate/_base.py
fenbux/multivariate/_dirichlet.py
fenbux/multivariate/_mvnormal.py
fenbux/scipy_stats/__init__.py
fenbux/scipy_stats/_dists.py
fenbux/scipy_stats/_wrapper.py
fenbux/univariate/__init__.py
fenbux/univariate/_base.py
fenbux/univariate/_censor.py
fenbux/univariate/_iid.py
fenbux/univariate/_loc_scale.py
fenbux/univariate/_truncate.py
fenbux/univariate/continuous/__init__.py
fenbux/univariate/continuous/_beta.py
fenbux/univariate/continuous/_cauchy.py
fenbux/univariate/continuous/_chisquare.py
fenbux/univariate/continuous/_exponential.py
fenbux-0.1.0.dist-info/LICENSE
fenbux-0.1.0.dist-info/METADATA
fenbux-0.1.0.dist-info/WHEEL
fenbux-0.1.0.dist-info/top_level.txt
fenbux-0.1.0.dist-info/RECORD
