Metadata-Version: 2.1
Name: fenbux
Version: 0.1.0
Summary: A Simple Statistical Distribution Library In JAX
Author-email: Yaobo Jia <leojia2001@gmail.com>
License: Apache License
Project-URL: repository, https://github.com/JiaYaobo/fenbux
Keywords: jax,statistics,probability,distribution
Requires-Python: ~=3.9
License-File: LICENSE
Requires-Dist: jax >=0.4.18
Requires-Dist: jaxtyping >=0.2.20
Requires-Dist: equinox >=0.10.11
Requires-Dist: typing-extensions >=4.5.0
Requires-Dist: tensorflow-probability >=0.20.1
Requires-Dist: fenbux-plum-dispatch >=0.0.2
